delab_trees/__init__.py
delab_trees/constants.py
delab_trees/delab_author_metric.py
delab_trees/delab_post.py
delab_trees/delab_tree.py
delab_trees/exceptions.py
delab_trees/flow_duos.py
delab_trees/main.py
delab_trees/parallel_utils.py
delab_trees/preperation_alg_pb.py
delab_trees/preperation_alg_rb.py
delab_trees/test_data_manager.py
delab_trees/training_alg_pb.py
delab_trees/training_alg_rb.py
delab_trees/util.py
delab_trees/data/__init__.py
delab_trees/data/dataset_reddit_no_text.pkl
delab_trees/data/dataset_twitter_no_text.pkl
delab_trees/recursive_tree/__init__.py
delab_trees/recursive_tree/recursive_tree.py
delab_trees/recursive_tree/recursive_tree_util.py
tests/__init__.py
tests/delab_tree_tests.py
tests/duo_flow_tests.py
tests/pb_algorithm_tests.py
tests/rb_algorithm_tests.py
tests/recursive_tree_tests.py
tests/run_tests.py
delab_trees-0.4.2.dist-info/LICENSE
delab_trees-0.4.2.dist-info/METADATA
delab_trees-0.4.2.dist-info/WHEEL
delab_trees-0.4.2.dist-info/top_level.txt
delab_trees-0.4.2.dist-info/RECORD
