Metadata-Version: 2.1
Name: delab-trees
Version: 0.4.2
Summary: a library to analyse reply trees in forums and social media
Home-page: https://github.com/juliandehne/delab-trees
Author: Julian Dehne
Author-email: julian.dehne@gmail.com
License: MIT
Classifier: Intended Audience :: Developers
Classifier: License :: OSI Approved :: MIT License
Classifier: Programming Language :: Python :: 3.9
Classifier: Operating System :: OS Independent
License-File: LICENSE
Requires-Dist: numpy
Requires-Dist: pandas
Requires-Dist: networkx
Requires-Dist: scikit-learn
Requires-Dist: keras
Requires-Dist: matplotlib
Requires-Dist: tensorflow
